logiq/__init__.py
logiq/creations/__init__.py
logiq/creations/algorithms.py
logiq/creations/protocols.py
logiq/src/Basis.py
logiq/src/Operator.py
logiq/src/Qbit.py
logiq/src/Qbits.py
logiq/src/Qerrors.py
logiq/src/Qmath.py
logiq/src/Qstate.py
logiq/src/__init__.py
logiq/src/abs_Qstate.py
logiq/src/qtils.py
logiq-0.1.3.dist-info/LICENSE
logiq-0.1.3.dist-info/METADATA
logiq-0.1.3.dist-info/WHEEL
logiq-0.1.3.dist-info/top_level.txt
logiq-0.1.3.dist-info/RECORD
