Metadata-Version: 2.1
Name: logiq
Version: 0.1.3
Summary: Logiq, a simple to use quantum simulator library
Home-page: https://github.com/Bnz-0/logiq
Author: Bnz
Author-email: matteo.benzi97@gmail.com
License: MIT License
Requires-Dist: numpy
